{
  "base": {
    "display": "block",
    "zIndex": "0",
    "top": "0px",
    "left": "0px",
    "width": "800px",
    "height": "534px",
    "borderRadius": "0px",
    "outline": "rgb(0, 0, 0) solid 0px",
    "outlineOffset": "0px",
    "boxShadow": "rgb(0, 0, 0) 0px 0px 0px 0px",
    "backgroundColor": "rgba(0, 0, 0, 0)",
    "backgroundImage": "url(\"https://chrisdejoya.github.io/Trailpad/beta/images/haute/base.svg\")",
    "backgroundSize": "contain",
    "color": "rgba(0, 0, 0, 0)",
    "fontSize": "0px",
    "label": ""
  },
  "joystick": {
    "display": "none",
    "zIndex": "1",
    "top": "60px",
    "left": "80px",
    "width": "210px",
    "height": "210px",
    "borderRadius": "0px",
    "outline": "rgb(238, 238, 238) none 0px",
    "outlineOffset": "0px",
    "boxShadow": "none",
    "backgroundColor": "rgba(0, 0, 0, 0)",
    "backgroundImage": "url(\"https://chrisdejoya.github.io/Trailpad/beta/images/gate_strive.svg\")",
    "backgroundSize": "cover",
    "color": "rgb(238, 238, 238)",
    "fontSize": "16px",
    "label": ""
  },
  "joystickHead": {
    "display": "flex",
    "zIndex": "4",
    "top": "0.0003814px",
    "left": "-0.0003814px",
    "width": "60px",
    "height": "60px",
    "borderRadius": "50%",
    "outline": "rgb(0, 0, 0) none 0px",
    "outlineOffset": "0px",
    "boxShadow": "none",
    "backgroundColor": "rgb(64, 64, 64)",
    "backgroundImage": "none",
    "backgroundSize": "auto",
    "color": "rgb(0, 0, 0)",
    "fontSize": "30px",
    "label": ""
  },
  "eightWayWrapper": {
    "display": "none",
    "zIndex": "auto",
    "top": "270px",
    "left": "70px",
    "width": "230px",
    "height": "230px",
    "borderRadius": "50%",
    "outline": "rgb(238, 238, 238) none 0px",
    "outlineOffset": "0px",
    "boxShadow": "none",
    "backgroundColor": "rgba(0, 0, 0, 0)",
    "backgroundImage": "url(\"https://chrisdejoya.github.io/Trailpad/images/sf/gate_strive.svg\")",
    "backgroundSize": "auto",
    "color": "rgb(238, 238, 238)",
    "fontSize": "16px",
    "label": "",
    "arrowSize": 90,
    "arrowImageOn": "https://chrisdejoya.github.io/Trailpad/beta/images/arrow-on.svg",
    "arrowImageOff": "https://chrisdejoya.github.io/Trailpad/beta/images/arrow-off.svg"
  },
  "buttons": {
    "Up": {
      "display": "flex",
      "zIndex": "2",
      "top": "293px",
      "left": "301px",
      "width": "90px",
      "height": "90px",
      "borderRadius": "45px",
      "outline": "rgb(0, 0, 0) solid 2px",
      "outlineOffset": "-2px",
      "boxShadow": "rgba(0, 0, 0, 0.5) 0px 5px 7px 0px",
      "backgroundColor": "rgb(153, 153, 153)",
      "backgroundImage": "url(\"https://chrisdejoya.github.io/Trailpad/beta/images/haute/btn-30.svg\")",
      "backgroundSize": "contain",
      "color": "rgb(0, 0, 0)",
      "fontSize": "49px",
      "label": ""
    },
    "Down": {
      "display": "flex",
      "zIndex": "2",
      "top": "124px",
      "left": "195px",
      "width": "80px",
      "height": "80px",
      "borderRadius": "40px",
      "outline": "rgb(0, 0, 0) solid 2px",
      "outlineOffset": "-2px",
      "boxShadow": "rgba(0, 0, 0, 0.5) 0px 5px 7px 0px",
      "backgroundColor": "rgb(153, 153, 153)",
      "backgroundImage": "url(\"https://chrisdejoya.github.io/Trailpad/beta/images/haute/btn-24.svg\")",
      "backgroundSize": "contain",
      "color": "rgb(0, 0, 0)",
      "fontSize": "49px",
      "label": ""
    },
    "Left": {
      "display": "flex",
      "zIndex": "2",
      "top": "125px",
      "left": "106px",
      "width": "80px",
      "height": "80px",
      "borderRadius": "40px",
      "outline": "rgb(0, 0, 0) solid 2px",
      "outlineOffset": "-2px",
      "boxShadow": "rgba(0, 0, 0, 0.5) 0px 5px 7px 0px",
      "backgroundColor": "rgb(153, 153, 153)",
      "backgroundImage": "url(\"https://chrisdejoya.github.io/Trailpad/beta/images/haute/btn-24.svg\")",
      "backgroundSize": "contain",
      "color": "rgb(0, 0, 0)",
      "fontSize": "49px",
      "label": ""
    },
    "Right": {
      "display": "flex",
      "zIndex": "2",
      "top": "164px",
      "left": "275px",
      "width": "80px",
      "height": "80px",
      "borderRadius": "40px",
      "outline": "rgb(0, 0, 0) solid 2px",
      "outlineOffset": "-2px",
      "boxShadow": "rgba(0, 0, 0, 0.5) 0px 5px 7px 0px",
      "backgroundColor": "rgb(153, 153, 153)",
      "backgroundImage": "url(\"https://chrisdejoya.github.io/Trailpad/beta/images/haute/btn-24.svg\")",
      "backgroundSize": "contain",
      "color": "rgb(0, 0, 0)",
      "fontSize": "49px",
      "label": ""
    },
    "A": {
      "display": "flex",
      "zIndex": "2",
      "top": "216px",
      "left": "350px",
      "width": "80px",
      "height": "80px",
      "borderRadius": "40px",
      "outline": "rgb(0, 0, 0) solid 2px",
      "outlineOffset": "-2px",
      "boxShadow": "rgba(0, 0, 0, 0.5) 0px 5px 7px 0px",
      "backgroundColor": "rgb(153, 153, 153)",
      "backgroundImage": "url(\"https://chrisdejoya.github.io/Trailpad/beta/images/haute/btn-24.svg\")",
      "backgroundSize": "contain",
      "color": "rgb(0, 0, 0)",
      "fontSize": "32px",
      "label": "S1"
    },
    "B": {
      "display": "flex",
      "zIndex": "2",
      "top": "180px",
      "left": "430px",
      "width": "80px",
      "height": "80px",
      "borderRadius": "40px",
      "outline": "rgb(0, 0, 0) solid 2px",
      "outlineOffset": "-2px",
      "boxShadow": "rgba(0, 0, 0, 0.5) 0px 5px 7px 0px",
      "backgroundColor": "rgb(153, 153, 153)",
      "backgroundImage": "url(\"https://chrisdejoya.github.io/Trailpad/beta/images/haute/btn-24.svg\")",
      "backgroundSize": "contain",
      "color": "rgb(0, 0, 0)",
      "fontSize": "32px",
      "label": "S2"
    },
    "X": {
      "display": "flex",
      "zIndex": "2",
      "top": "125px",
      "left": "356px",
      "width": "80px",
      "height": "80px",
      "borderRadius": "40px",
      "outline": "rgb(0, 0, 0) solid 2px",
      "outlineOffset": "-2px",
      "boxShadow": "rgba(0, 0, 0, 0.5) 0px 5px 7px 0px",
      "backgroundColor": "rgb(153, 153, 153)",
      "backgroundImage": "url(\"https://chrisdejoya.github.io/Trailpad/beta/images/haute/btn-24.svg\")",
      "backgroundSize": "contain",
      "color": "rgb(0, 0, 0)",
      "fontSize": "34px",
      "label": "l"
    },
    "Y": {
      "display": "flex",
      "zIndex": "2",
      "top": "90px",
      "left": "438px",
      "width": "80px",
      "height": "80px",
      "borderRadius": "40px",
      "outline": "rgb(0, 0, 0) solid 2px",
      "outlineOffset": "-2px",
      "boxShadow": "rgba(0, 0, 0, 0.5) 0px 5px 7px 0px",
      "backgroundColor": "rgb(153, 153, 153)",
      "backgroundImage": "url(\"https://chrisdejoya.github.io/Trailpad/beta/images/haute/btn-24.svg\")",
      "backgroundSize": "contain",
      "color": "rgb(0, 0, 0)",
      "fontSize": "32px",
      "label": "m"
    },
    "LB": {
      "display": "flex",
      "zIndex": "2",
      "top": "101px",
      "left": "611px",
      "width": "80px",
      "height": "80px",
      "borderRadius": "40px",
      "outline": "rgb(0, 0, 0) solid 2px",
      "outlineOffset": "-2px",
      "boxShadow": "rgba(0, 0, 0, 0.5) 0px 5px 7px 0px",
      "backgroundColor": "rgb(153, 153, 153)",
      "backgroundImage": "url(\"https://chrisdejoya.github.io/Trailpad/beta/images/haute/btn-24.svg\")",
      "backgroundSize": "contain",
      "color": "rgb(0, 0, 0)",
      "fontSize": "32px",
      "label": "d"
    },
    "RB": {
      "display": "flex",
      "zIndex": "2",
      "top": "93px",
      "left": "525px",
      "width": "80px",
      "height": "80px",
      "borderRadius": "40px",
      "outline": "rgb(0, 0, 0) solid 2px",
      "outlineOffset": "-2px",
      "boxShadow": "rgba(0, 0, 0, 0.5) 0px 5px 7px 0px",
      "backgroundColor": "rgb(153, 153, 153)",
      "backgroundImage": "url(\"https://chrisdejoya.github.io/Trailpad/beta/images/haute/btn-24.svg\")",
      "backgroundSize": "contain",
      "color": "rgb(0, 0, 0)",
      "fontSize": "32px",
      "label": "h"
    },
    "LT": {
      "display": "flex",
      "zIndex": "2",
      "top": "190px",
      "left": "606px",
      "width": "80px",
      "height": "80px",
      "borderRadius": "40px",
      "outline": "rgb(0, 0, 0) solid 2px",
      "outlineOffset": "-2px",
      "boxShadow": "rgba(0, 0, 0, 0.5) 0px 5px 7px 0px",
      "backgroundColor": "rgb(153, 153, 153)",
      "backgroundImage": "url(\"https://chrisdejoya.github.io/Trailpad/beta/images/haute/btn-24.svg\")",
      "backgroundSize": "contain",
      "color": "rgb(0, 0, 0)",
      "fontSize": "32px",
      "label": "P"
    },
    "RT": {
      "display": "flex",
      "zIndex": "2",
      "top": "183px",
      "left": "519px",
      "width": "80px",
      "height": "80px",
      "borderRadius": "40px",
      "outline": "rgb(0, 0, 0) solid 2px",
      "outlineOffset": "-2px",
      "boxShadow": "rgba(0, 0, 0, 0.5) 0px 5px 7px 0px",
      "backgroundColor": "rgb(153, 153, 153)",
      "backgroundImage": "url(\"https://chrisdejoya.github.io/Trailpad/beta/images/haute/btn-24.svg\")",
      "backgroundSize": "contain",
      "color": "rgb(0, 0, 0)",
      "fontSize": "32px",
      "label": "t"
    },
    "LS": {
      "display": "flex",
      "zIndex": "4",
      "top": "12px",
      "left": "577px",
      "width": "30px",
      "height": "30px",
      "borderRadius": "15px",
      "outline": "rgb(0, 0, 0) solid 1px",
      "outlineOffset": "-1px",
      "boxShadow": "rgba(0, 0, 0, 0.5) 0px 3px 5px 0px",
      "backgroundColor": "rgb(153, 153, 153)",
      "backgroundImage": "url(\"https://chrisdejoya.github.io/Trailpad/beta/images/haute/btn-8.svg\")",
      "backgroundSize": "contain",
      "color": "rgba(0, 0, 0, 0)",
      "fontSize": "0px",
      "label": ""
    },
    "RS": {
      "display": "flex",
      "zIndex": "4",
      "top": "12px",
      "left": "622px",
      "width": "30px",
      "height": "30px",
      "borderRadius": "15px",
      "outline": "rgb(0, 0, 0) solid 1px",
      "outlineOffset": "-1px",
      "boxShadow": "rgba(0, 0, 0, 0.5) 0px 3px 5px 0px",
      "backgroundColor": "rgb(153, 153, 153)",
      "backgroundImage": "url(\"https://chrisdejoya.github.io/Trailpad/beta/images/haute/btn-8.svg\")",
      "backgroundSize": "contain",
      "color": "rgba(0, 0, 0, 0)",
      "fontSize": "0px",
      "label": ""
    },
    "View": {
      "display": "flex",
      "zIndex": "2",
      "top": "12px",
      "left": "668px",
      "width": "30px",
      "height": "30px",
      "borderRadius": "15px",
      "outline": "rgb(0, 0, 0) solid 1px",
      "outlineOffset": "-1px",
      "boxShadow": "rgba(0, 0, 0, 0.5) 0px 3px 5px 0px",
      "backgroundColor": "rgb(153, 153, 153)",
      "backgroundImage": "url(\"https://chrisdejoya.github.io/Trailpad/beta/images/haute/btn-8.svg\")",
      "backgroundSize": "contain",
      "color": "rgba(0, 0, 0, 0)",
      "fontSize": "0px",
      "label": ""
    },
    "Menu": {
      "display": "flex",
      "zIndex": "2",
      "top": "12px",
      "left": "713px",
      "width": "30px",
      "height": "30px",
      "borderRadius": "15px",
      "outline": "rgb(0, 0, 0) solid 1px",
      "outlineOffset": "-1px",
      "boxShadow": "rgba(0, 0, 0, 0.5) 0px 3px 5px 0px",
      "backgroundColor": "rgb(153, 153, 153)",
      "backgroundImage": "url(\"https://chrisdejoya.github.io/Trailpad/beta/images/haute/btn-8.svg\")",
      "backgroundSize": "contain",
      "color": "rgba(0, 0, 0, 0)",
      "fontSize": "0px",
      "label": ""
    }
  },
  "trailColor": "#eedd44",
  "analog": {
    "LS": false,
    "RS": false,
    "analogVisualRange": 10,
    "pressureEnabled": false,
    "minTriggerBrightness": 1,
    "maxTriggerBrightness": 3,
    "triggerDeadzone": 0
  }
}