{
  "base": {
    "display": "none",
    "zIndex": "0",
    "top": "50px",
    "left": "80px",
    "width": "640px",
    "height": "240px",
    "borderRadius": "0px",
    "outline": "rgba(0, 0, 0, 0.3) solid 6px",
    "outlineOffset": "-6px",
    "boxShadow": "none",
    "backgroundColor": "rgba(0, 0, 0, 0.6)",
    "backgroundImage": "none",
    "backgroundSize": "auto",
    "color": "rgb(238, 238, 238)",
    "fontSize": "16px",
    "label": ""
  },
  "joystick": {
    "display": "block",
    "zIndex": "2",
    "top": "120px",
    "left": "140px",
    "width": "110px",
    "height": "110px",
    "borderRadius": "0px",
    "outline": "rgb(238, 238, 238) none 0px",
    "outlineOffset": "0px",
    "boxShadow": "none",
    "backgroundColor": "rgba(0, 0, 0, 0)",
    "backgroundImage": "none",
    "backgroundSize": "cover",
    "color": "rgb(238, 238, 238)",
    "fontSize": "16px",
    "label": ""
  },
  "joystickHead": {
    "display": "flex",
    "zIndex": "4",
    "top": "55px",
    "left": "55px",
    "width": "70px",
    "height": "70px",
    "borderRadius": "50%",
    "outline": "rgb(255, 255, 255) none 0px",
    "outlineOffset": "0px",
    "boxShadow": "rgb(0, 0, 0) 0px 0px 5px 2px",
    "backgroundColor": "rgb(80, 80, 80)",
    "backgroundImage": "url(\"https://chrisdejoya.github.io/Trailpad/images/sf/sf-joystick.svg\")",
    "backgroundSize": "contain",
    "color": "rgb(0, 0, 0)",
    "fontSize": "30px",
    "label": ""
  },
  "eightWayWrapper": {
    "display": "block",
    "zIndex": "1",
    "top": "60px",
    "left": "80px",
    "width": "230px",
    "height": "230px",
    "borderRadius": "50%",
    "outline": "rgb(238, 238, 238) none 0px",
    "outlineOffset": "0px",
    "boxShadow": "none",
    "backgroundColor": "rgba(0, 0, 0, 0)",
    "backgroundImage": "url(\"https://chrisdejoya.github.io/Trailpad/images/sf/gate_strive.svg\")",
    "backgroundSize": "auto",
    "color": "rgb(238, 238, 238)",
    "fontSize": "16px",
    "label": "",
    "arrowSize": 100,
    "arrowImageOn": "https://chrisdejoya.github.io/Trailpad/images/sf/sf-arrow-on.svg",
    "arrowImageOff": "https://chrisdejoya.github.io/Trailpad/images/sf/sf-arrow-off.svg"
  },
  "buttons": {
    "Up": {
      "display": "none",
      "zIndex": "2",
      "top": "270px",
      "left": "300px",
      "width": "90px",
      "height": "90px",
      "borderRadius": "0px",
      "outline": "rgba(255, 255, 255, 0.18) solid 4px",
      "outlineOffset": "-4px",
      "boxShadow": "rgb(0, 0, 0) 0px 0px 0px 4px",
      "backgroundColor": "rgb(48, 48, 48)",
      "backgroundImage": "url(\"https://chrisdejoya.github.io/Trailpad/images/up.svg\")",
      "backgroundSize": "contain",
      "color": "rgb(238, 238, 238)",
      "fontSize": "44px",
      "label": ""
    },
    "Down": {
      "display": "none",
      "zIndex": "2",
      "top": "270px",
      "left": "400px",
      "width": "90px",
      "height": "90px",
      "borderRadius": "0px",
      "outline": "rgba(255, 255, 255, 0.18) solid 4px",
      "outlineOffset": "-4px",
      "boxShadow": "rgb(0, 0, 0) 0px 0px 0px 4px",
      "backgroundColor": "rgb(48, 48, 48)",
      "backgroundImage": "url(\"https://chrisdejoya.github.io/Trailpad/images/down.svg\")",
      "backgroundSize": "contain",
      "color": "rgb(238, 238, 238)",
      "fontSize": "44px",
      "label": ""
    },
    "Left": {
      "display": "none",
      "zIndex": "2",
      "top": "270px",
      "left": "500px",
      "width": "90px",
      "height": "90px",
      "borderRadius": "0px",
      "outline": "rgba(255, 255, 255, 0.18) solid 4px",
      "outlineOffset": "-4px",
      "boxShadow": "rgb(0, 0, 0) 0px 0px 0px 4px",
      "backgroundColor": "rgb(48, 48, 48)",
      "backgroundImage": "url(\"https://chrisdejoya.github.io/Trailpad/images/left.svg\")",
      "backgroundSize": "contain",
      "color": "rgb(238, 238, 238)",
      "fontSize": "44px",
      "label": ""
    },
    "Right": {
      "display": "none",
      "zIndex": "2",
      "top": "270px",
      "left": "600px",
      "width": "90px",
      "height": "90px",
      "borderRadius": "0px",
      "outline": "rgba(255, 255, 255, 0.18) solid 4px",
      "outlineOffset": "-4px",
      "boxShadow": "rgb(0, 0, 0) 0px 0px 0px 4px",
      "backgroundColor": "rgb(48, 48, 48)",
      "backgroundImage": "url(\"https://chrisdejoya.github.io/Trailpad/images/right.svg\")",
      "backgroundSize": "contain",
      "color": "rgb(238, 238, 238)",
      "fontSize": "44px",
      "label": ""
    },
    "A": {
      "display": "flex",
      "zIndex": "2",
      "top": "180px",
      "left": "310px",
      "width": "90px",
      "height": "90px",
      "borderRadius": "45px",
      "outline": "rgb(153, 153, 255) solid 4px",
      "outlineOffset": "-4px",
      "boxShadow": "rgba(0, 0, 0, 0.5) 0px 0px 5px 2px",
      "backgroundColor": "rgba(128, 128, 255, 0.9)",
      "backgroundImage": "url(\"https://chrisdejoya.github.io/Trailpad/images/sf/sf-kick.svg\")",
      "backgroundSize": "contain",
      "color": "rgba(238, 238, 238, 0.9)",
      "fontSize": "0px",
      "label": "lk"
    },
    "B": {
      "display": "flex",
      "zIndex": "2",
      "top": "180px",
      "left": "410px",
      "width": "90px",
      "height": "90px",
      "borderRadius": "45px",
      "outline": "rgb(57, 204, 57) solid 4px",
      "outlineOffset": "-4px",
      "boxShadow": "rgba(0, 0, 0, 0.5) 0px 0px 5px 2px",
      "backgroundColor": "rgba(45, 179, 45, 0.9)",
      "backgroundImage": "url(\"https://chrisdejoya.github.io/Trailpad/images/sf/sf-kick.svg\")",
      "backgroundSize": "contain",
      "color": "rgba(238, 238, 238, 0.9)",
      "fontSize": "0px",
      "label": "mk"
    },
    "X": {
      "display": "flex",
      "zIndex": "2",
      "top": "70px",
      "left": "310px",
      "width": "90px",
      "height": "90px",
      "borderRadius": "45px",
      "outline": "rgb(153, 153, 255) solid 4px",
      "outlineOffset": "-4px",
      "boxShadow": "rgba(0, 0, 0, 0.5) 0px 0px 5px 2px",
      "backgroundColor": "rgba(128, 128, 255, 0.9)",
      "backgroundImage": "url(\"https://chrisdejoya.github.io/Trailpad/images/sf/sf-punch.svg\")",
      "backgroundSize": "contain",
      "color": "rgba(238, 238, 238, 0.9)",
      "fontSize": "0px",
      "label": "lp"
    },
    "Y": {
      "display": "flex",
      "zIndex": "2",
      "top": "70px",
      "left": "410px",
      "width": "90px",
      "height": "90px",
      "borderRadius": "45px",
      "outline": "rgb(57, 204, 57) solid 4px",
      "outlineOffset": "-4px",
      "boxShadow": "rgba(0, 0, 0, 0.5) 0px 0px 5px 2px",
      "backgroundColor": "rgba(45, 179, 45, 0.9)",
      "backgroundImage": "url(\"https://chrisdejoya.github.io/Trailpad/images/sf/sf-punch.svg\")",
      "backgroundSize": "100px auto",
      "color": "rgba(238, 238, 238, 0.9)",
      "fontSize": "0px",
      "label": "mp"
    },
    "LB": {
      "display": "flex",
      "zIndex": "2",
      "top": "70px",
      "left": "610px",
      "width": "90px",
      "height": "90px",
      "borderRadius": "45px",
      "outline": "rgb(85, 32, 153) solid 4px",
      "outlineOffset": "-4px",
      "boxShadow": "rgba(0, 0, 0, 0.5) 0px 0px 5px 2px",
      "backgroundColor": "rgb(51, 13, 102)",
      "backgroundImage": "none",
      "backgroundSize": "contain",
      "color": "rgba(238, 238, 238, 0.9)",
      "fontSize": "28px",
      "label": "DI"
    },
    "RB": {
      "display": "flex",
      "zIndex": "2",
      "top": "70px",
      "left": "510px",
      "width": "90px",
      "height": "90px",
      "borderRadius": "45px",
      "outline": "rgb(230, 77, 77) solid 4px",
      "outlineOffset": "-4px",
      "boxShadow": "rgba(0, 0, 0, 0.5) 0px 0px 5px 2px",
      "backgroundColor": "rgba(204, 58, 58, 0.9)",
      "backgroundImage": "url(\"https://chrisdejoya.github.io/Trailpad/images/sf/sf-punch.svg\")",
      "backgroundSize": "100px auto",
      "color": "rgba(238, 238, 238, 0.9)",
      "fontSize": "0px",
      "label": "hp"
    },
    "LT": {
      "display": "flex",
      "zIndex": "2",
      "top": "180px",
      "left": "610px",
      "width": "90px",
      "height": "90px",
      "borderRadius": "45px",
      "outline": "rgb(32, 128, 32) solid 4px",
      "outlineOffset": "-4px",
      "boxShadow": "rgba(0, 0, 0, 0.5) 0px 0px 5px 2px",
      "backgroundColor": "rgba(13, 102, 13, 0.9)",
      "backgroundImage": "none",
      "backgroundSize": "contain",
      "color": "rgb(238, 238, 238)",
      "fontSize": "28px",
      "label": "P"
    },
    "RT": {
      "display": "flex",
      "zIndex": "2",
      "top": "180px",
      "left": "510px",
      "width": "90px",
      "height": "90px",
      "borderRadius": "45px",
      "outline": "rgb(230, 77, 77) solid 4px",
      "outlineOffset": "-4px",
      "boxShadow": "rgba(0, 0, 0, 0.5) 0px 0px 5px 2px",
      "backgroundColor": "rgba(204, 58, 58, 0.9)",
      "backgroundImage": "url(\"https://chrisdejoya.github.io/Trailpad/images/sf/sf-kick.svg\")",
      "backgroundSize": "contain",
      "color": "rgba(238, 238, 238, 0.9)",
      "fontSize": "0px",
      "label": "hk"
    },
    "LS": {
      "display": "none",
      "zIndex": "4",
      "top": "370px",
      "left": "300px",
      "width": "90px",
      "height": "90px",
      "borderRadius": "0px",
      "outline": "rgba(255, 255, 255, 0.18) solid 4px",
      "outlineOffset": "-4px",
      "boxShadow": "rgb(0, 0, 0) 0px 0px 0px 4px",
      "backgroundColor": "rgb(48, 48, 48)",
      "backgroundImage": "none",
      "backgroundSize": "contain",
      "color": "rgb(238, 238, 238)",
      "fontSize": "36px",
      "label": "LS"
    },
    "RS": {
      "display": "none",
      "zIndex": "4",
      "top": "370px",
      "left": "400px",
      "width": "90px",
      "height": "90px",
      "borderRadius": "0px",
      "outline": "rgba(255, 255, 255, 0.18) solid 4px",
      "outlineOffset": "-4px",
      "boxShadow": "rgb(0, 0, 0) 0px 0px 0px 4px",
      "backgroundColor": "rgb(48, 48, 48)",
      "backgroundImage": "none",
      "backgroundSize": "contain",
      "color": "rgb(238, 238, 238)",
      "fontSize": "36px",
      "label": "RS"
    },
    "View": {
      "display": "none",
      "zIndex": "2",
      "top": "370px",
      "left": "500px",
      "width": "90px",
      "height": "90px",
      "borderRadius": "0px",
      "outline": "rgba(255, 255, 255, 0.18) solid 4px",
      "outlineOffset": "-4px",
      "boxShadow": "rgb(0, 0, 0) 0px 0px 0px 4px",
      "backgroundColor": "rgb(48, 48, 48)",
      "backgroundImage": "none",
      "backgroundSize": "contain",
      "color": "rgb(238, 238, 238)",
      "fontSize": "20px",
      "label": "View"
    },
    "Menu": {
      "display": "none",
      "zIndex": "2",
      "top": "370px",
      "left": "600px",
      "width": "90px",
      "height": "90px",
      "borderRadius": "0px",
      "outline": "rgba(255, 255, 255, 0.18) solid 4px",
      "outlineOffset": "-4px",
      "boxShadow": "rgb(0, 0, 0) 0px 0px 0px 4px",
      "backgroundColor": "rgb(48, 48, 48)",
      "backgroundImage": "none",
      "backgroundSize": "contain",
      "color": "rgb(238, 238, 238)",
      "fontSize": "20px",
      "label": "Menu"
    }
  },
  "trailColor": "#00000000"
}
